vibelab/__init__.py
vibelab/hatch_build.py
vibelab/lib.py
vibelab/models_registry.py
vibelab/pricing.py
vibelab/api/__init__.py
vibelab/api/admin.py
vibelab/api/app.py
vibelab/api/datasets.py
vibelab/api/executors.py
vibelab/api/judges.py
vibelab/api/pairwise.py
vibelab/api/projects.py
vibelab/api/results.py
vibelab/api/review_queue.py
vibelab/api/runs.py
vibelab/api/scenarios.py
vibelab/api/streaming.py
vibelab/api/tasks.py
vibelab/cli/__init__.py
vibelab/cli/console.py
vibelab/cli/dataset.py
vibelab/cli/executor.py
vibelab/cli/main.py
vibelab/cli/result.py
vibelab/cli/run.py
vibelab/cli/scenario.py
vibelab/cli/start.py
vibelab/db/__init__.py
vibelab/db/connection.py
vibelab/db/migrations.py
vibelab/db/queries.py
vibelab/drivers/__init__.py
vibelab/drivers/base.py
vibelab/drivers/docker.py
vibelab/drivers/local.py
vibelab/drivers/modal.py
vibelab/drivers/orbstack.py
vibelab/engine/__init__.py
vibelab/engine/commit_analyzer.py
vibelab/engine/judge.py
vibelab/engine/loader.py
vibelab/engine/metrics.py
vibelab/engine/queue.py
vibelab/engine/repo_cache.py
vibelab/engine/runner.py
vibelab/engine/streaming.py
vibelab/engine/task_executor.py
vibelab/engine/worker.py
vibelab/harnesses/__init__.py
vibelab/harnesses/base.py
vibelab/harnesses/claude_code.py
vibelab/harnesses/cursor.py
vibelab/harnesses/gemini.py
vibelab/harnesses/openai_codex.py
vibelab/harnesses/usage.py
vibelab/models/__init__.py
vibelab/models/commit_draft.py
vibelab/models/dataset.py
vibelab/models/executor.py
vibelab/models/judge.py
vibelab/models/pairwise.py
vibelab/models/project.py
vibelab/models/result.py
vibelab/models/scenario.py
vibelab/web/dist/favicon.svg
vibelab/web/dist/index.html
vibelab/web/dist/assets/index-BXaJZKVa.css
vibelab/web/dist/assets/index-ayAaNjqu.js
vibelab-0.0.7.dist-info/METADATA
vibelab-0.0.7.dist-info/WHEEL
vibelab-0.0.7.dist-info/entry_points.txt
vibelab-0.0.7.dist-info/RECORD
