Metadata-Version: 2.4
Name: vibelab
Version: 0.0.7
Summary: Rigorous evaluation tool for comparing LLM coding agents
Author: VibeLab Contributors
License: PolyForm Noncommercial 1.0.0
Requires-Python: >=3.11
Requires-Dist: aiofiles>=23.0.0
Requires-Dist: anthropic>=0.18.0
Requires-Dist: fastapi>=0.104.0
Requires-Dist: litellm>=1.50.0
Requires-Dist: openai>=1.0.0
Requires-Dist: pydantic>=2.0.0
Requires-Dist: typer>=0.9.0
Requires-Dist: uvicorn>=0.24.0
Provides-Extra: all-drivers
Requires-Dist: docker>=6.0.0; extra == 'all-drivers'
Requires-Dist: modal>=0.60.0; extra == 'all-drivers'
Provides-Extra: dev
Requires-Dist: mypy>=1.7.0; extra == 'dev'
Requires-Dist: pytest>=7.4.0; extra == 'dev'
Requires-Dist: ruff>=0.1.0; extra == 'dev'
Provides-Extra: docker
Requires-Dist: docker>=6.0.0; extra == 'docker'
Provides-Extra: modal
Requires-Dist: modal>=0.60.0; extra == 'modal'
Provides-Extra: orbstack
Requires-Dist: docker>=6.0.0; extra == 'orbstack'
